{
  "id": "677545f504951e17f37fb1ec",
  "datasetId": "67753ec471a6654d3f980dab",
  "url": "https://rc-gate.dataloop.ai/api/v1/items/677545f504951e17f37fb1ec",
  "dataset": "https://rc-gate.dataloop.ai/api/v1/datasets/67753ec471a6654d3f980dab",
  "createdAt": "2025-01-01T13:41:09.310Z",
  "dir": "/",
  "filename": "/20504.json",
  "type": "file",
  "hidden": false,
  "metadata": {
    "system": {
      "encoding": "7bit",
      "isBinary": false,
      "mimetype": "application/json",
      "originalname": "20504.json",
      "refs": [],
      "shebang": {
        "dltype": "prompt"
      },
      "size": 240,
      "tags": {
        "train": true
      },
      "taskStatusLog": []
    }
  },
  "name": "20504.json",
  "creator": "yaya.t@dataloop.ai",
  "updatedAt": "2025-01-02T05:02:41.079Z",
  "updatedBy": "rubiks@dataloop.ai",
  "stream": "https://rc-gate.dataloop.ai/api/v1/items/677545f504951e17f37fb1ec/stream",
  "thumbnail": "https://rc-gate.dataloop.ai/api/v1/items/677545f504951e17f37fb1ec/thumbnail",
  "annotations": [
    {
      "id": "6775a35e83871c499606b10e",
      "datasetId": "67753ec471a6654d3f980dab",
      "itemId": "677545f504951e17f37fb1ec",
      "url": "https://rc-gate.dataloop.ai/api/v1/annotations/6775a35e83871c499606b10e",
      "item": "https://rc-gate.dataloop.ai/api/v1/items/677545f504951e17f37fb1ec",
      "dataset": "https://rc-gate.dataloop.ai/api/v1/datasets/67753ec471a6654d3f980dab",
      "type": "text",
      "label": "free-text",
      "coordinates": "This is a photo of Bags from Women's Accessories",
      "metadata": {
        "system": {
          "automated": true,
          "promptId": "1"
        },
        "user": {}
      },
      "creator": "yaya.t@dataloop.ai",
      "createdAt": "2025-01-01T20:19:42.680Z",
      "updatedBy": "yaya.t@dataloop.ai",
      "updatedAt": "2025-01-01T20:19:42.680Z",
      "hash": "00ecfb8c545e9743b6f3702124e01534e94f1994",
      "source": "sdk"
    }
  ],
  "annotationsCount": 1,
  "annotated": true
}