{
  "id": "6775469ae2d1e3717a8def37",
  "datasetId": "67753ec471a6654d3f980dab",
  "url": "https://rc-gate.dataloop.ai/api/v1/items/6775469ae2d1e3717a8def37",
  "dataset": "https://rc-gate.dataloop.ai/api/v1/datasets/67753ec471a6654d3f980dab",
  "createdAt": "2025-01-01T13:43:54.264Z",
  "dir": "/",
  "filename": "/20799.json",
  "type": "file",
  "hidden": false,
  "metadata": {
    "system": {
      "encoding": "7bit",
      "isBinary": false,
      "mimetype": "application/json",
      "originalname": "20799.json",
      "refs": [],
      "shebang": {
        "dltype": "prompt"
      },
      "size": 240,
      "tags": {
        "train": true
      },
      "taskStatusLog": []
    }
  },
  "name": "20799.json",
  "creator": "yaya.t@dataloop.ai",
  "updatedAt": "2025-01-02T05:02:41.078Z",
  "updatedBy": "rubiks@dataloop.ai",
  "stream": "https://rc-gate.dataloop.ai/api/v1/items/6775469ae2d1e3717a8def37/stream",
  "thumbnail": "https://rc-gate.dataloop.ai/api/v1/items/6775469ae2d1e3717a8def37/thumbnail",
  "annotations": [
    {
      "id": "6775a3f083871c84d206ba7d",
      "datasetId": "67753ec471a6654d3f980dab",
      "itemId": "6775469ae2d1e3717a8def37",
      "url": "https://rc-gate.dataloop.ai/api/v1/annotations/6775a3f083871c84d206ba7d",
      "item": "https://rc-gate.dataloop.ai/api/v1/items/6775469ae2d1e3717a8def37",
      "dataset": "https://rc-gate.dataloop.ai/api/v1/datasets/67753ec471a6654d3f980dab",
      "type": "text",
      "label": "free-text",
      "coordinates": "This is a photo of Shoes from Men's Footwear",
      "metadata": {
        "system": {
          "automated": true,
          "promptId": "1"
        },
        "user": {}
      },
      "creator": "yaya.t@dataloop.ai",
      "createdAt": "2025-01-01T20:22:08.829Z",
      "updatedBy": "yaya.t@dataloop.ai",
      "updatedAt": "2025-01-01T20:22:08.829Z",
      "hash": "c19491e8e9abb04609064199f7d33ee58f5f9a72",
      "source": "sdk"
    }
  ],
  "annotationsCount": 1,
  "annotated": true
}