{
  "id": "677549a65cdbbe378cdc8544",
  "datasetId": "67753ec471a6654d3f980dab",
  "url": "https://rc-gate.dataloop.ai/api/v1/items/677549a65cdbbe378cdc8544",
  "dataset": "https://rc-gate.dataloop.ai/api/v1/datasets/67753ec471a6654d3f980dab",
  "createdAt": "2025-01-01T13:56:54.483Z",
  "dir": "/",
  "filename": "/25391.json",
  "type": "file",
  "hidden": false,
  "metadata": {
    "system": {
      "encoding": "7bit",
      "isBinary": false,
      "mimetype": "application/json",
      "originalname": "25391.json",
      "refs": [],
      "shebang": {
        "dltype": "prompt"
      },
      "size": 240,
      "tags": {
        "train": true
      },
      "taskStatusLog": []
    }
  },
  "name": "25391.json",
  "creator": "yaya.t@dataloop.ai",
  "updatedAt": "2025-01-02T05:02:42.068Z",
  "updatedBy": "rubiks@dataloop.ai",
  "stream": "https://rc-gate.dataloop.ai/api/v1/items/677549a65cdbbe378cdc8544/stream",
  "thumbnail": "https://rc-gate.dataloop.ai/api/v1/items/677549a65cdbbe378cdc8544/thumbnail",
  "annotations": [
    {
      "id": "6775a5ab0d0617eae16ead54",
      "datasetId": "67753ec471a6654d3f980dab",
      "itemId": "677549a65cdbbe378cdc8544",
      "url": "https://rc-gate.dataloop.ai/api/v1/annotations/6775a5ab0d0617eae16ead54",
      "item": "https://rc-gate.dataloop.ai/api/v1/items/677549a65cdbbe378cdc8544",
      "dataset": "https://rc-gate.dataloop.ai/api/v1/datasets/67753ec471a6654d3f980dab",
      "type": "text",
      "label": "free-text",
      "coordinates": "This is a photo of Innerwear from Men's Apparel",
      "metadata": {
        "system": {
          "automated": true,
          "promptId": "1"
        },
        "user": {}
      },
      "creator": "yaya.t@dataloop.ai",
      "createdAt": "2025-01-01T20:29:31.439Z",
      "updatedBy": "yaya.t@dataloop.ai",
      "updatedAt": "2025-01-01T20:29:31.439Z",
      "hash": "05ba3a35f78c7490faebc540e4328cf73bdc2795",
      "source": "sdk"
    }
  ],
  "annotationsCount": 1,
  "annotated": true
}