{
  "id": "67754af75cdbbe1f8fdc9fe3",
  "datasetId": "67753ec471a6654d3f980dab",
  "url": "https://rc-gate.dataloop.ai/api/v1/items/67754af75cdbbe1f8fdc9fe3",
  "dataset": "https://rc-gate.dataloop.ai/api/v1/datasets/67753ec471a6654d3f980dab",
  "createdAt": "2025-01-01T14:02:31.677Z",
  "dir": "/",
  "filename": "/32399.json",
  "type": "file",
  "hidden": false,
  "metadata": {
    "system": {
      "encoding": "7bit",
      "isBinary": false,
      "mimetype": "application/json",
      "originalname": "32399.json",
      "refs": [],
      "shebang": {
        "dltype": "prompt"
      },
      "size": 240,
      "tags": {
        "train": true
      },
      "taskStatusLog": []
    }
  },
  "name": "32399.json",
  "creator": "yaya.t@dataloop.ai",
  "updatedAt": "2025-01-02T05:02:42.068Z",
  "updatedBy": "rubiks@dataloop.ai",
  "stream": "https://rc-gate.dataloop.ai/api/v1/items/67754af75cdbbe1f8fdc9fe3/stream",
  "thumbnail": "https://rc-gate.dataloop.ai/api/v1/items/67754af75cdbbe1f8fdc9fe3/thumbnail",
  "annotations": [
    {
      "id": "6775b4aba53101fc410c53c9",
      "datasetId": "67753ec471a6654d3f980dab",
      "itemId": "67754af75cdbbe1f8fdc9fe3",
      "url": "https://rc-gate.dataloop.ai/api/v1/annotations/6775b4aba53101fc410c53c9",
      "item": "https://rc-gate.dataloop.ai/api/v1/items/67754af75cdbbe1f8fdc9fe3",
      "dataset": "https://rc-gate.dataloop.ai/api/v1/datasets/67753ec471a6654d3f980dab",
      "type": "text",
      "label": "free-text",
      "coordinates": "This is a photo of Topwear from Women's Apparel",
      "metadata": {
        "system": {
          "automated": true,
          "promptId": "1"
        },
        "user": {}
      },
      "creator": "yaya.t@dataloop.ai",
      "createdAt": "2025-01-01T21:33:31.508Z",
      "updatedBy": "yaya.t@dataloop.ai",
      "updatedAt": "2025-01-01T21:33:31.508Z",
      "hash": "17a9bf3d835a6f3dd9e853bf2383c91fd264c287",
      "source": "sdk"
    }
  ],
  "annotationsCount": 1,
  "annotated": true
}