{
  "id": "6775485e04951e5e1c7ff09f",
  "datasetId": "67753ec471a6654d3f980dab",
  "url": "https://rc-gate.dataloop.ai/api/v1/items/6775485e04951e5e1c7ff09f",
  "dataset": "https://rc-gate.dataloop.ai/api/v1/datasets/67753ec471a6654d3f980dab",
  "createdAt": "2025-01-01T13:51:26.524Z",
  "dir": "/",
  "filename": "/34274.json",
  "type": "file",
  "hidden": false,
  "metadata": {
    "system": {
      "encoding": "7bit",
      "isBinary": false,
      "mimetype": "application/json",
      "originalname": "34274.json",
      "refs": [],
      "shebang": {
        "dltype": "prompt"
      },
      "size": 240,
      "tags": {
        "train": true
      },
      "taskStatusLog": []
    }
  },
  "name": "34274.json",
  "creator": "yaya.t@dataloop.ai",
  "updatedAt": "2025-01-02T05:02:40.515Z",
  "updatedBy": "rubiks@dataloop.ai",
  "stream": "https://rc-gate.dataloop.ai/api/v1/items/6775485e04951e5e1c7ff09f/stream",
  "thumbnail": "https://rc-gate.dataloop.ai/api/v1/items/6775485e04951e5e1c7ff09f/thumbnail",
  "annotations": [
    {
      "id": "6775a5b80d0617a1836eae32",
      "datasetId": "67753ec471a6654d3f980dab",
      "itemId": "6775485e04951e5e1c7ff09f",
      "url": "https://rc-gate.dataloop.ai/api/v1/annotations/6775a5b80d0617a1836eae32",
      "item": "https://rc-gate.dataloop.ai/api/v1/items/6775485e04951e5e1c7ff09f",
      "dataset": "https://rc-gate.dataloop.ai/api/v1/datasets/67753ec471a6654d3f980dab",
      "type": "text",
      "label": "free-text",
      "coordinates": "This is a photo of Topwear from Women's Apparel",
      "metadata": {
        "system": {
          "automated": true,
          "promptId": "1"
        },
        "user": {}
      },
      "creator": "yaya.t@dataloop.ai",
      "createdAt": "2025-01-01T20:29:44.825Z",
      "updatedBy": "yaya.t@dataloop.ai",
      "updatedAt": "2025-01-01T20:29:44.825Z",
      "hash": "42bd53bd4faa35dffe42f0cffa4c70af8ff044c0",
      "source": "sdk"
    }
  ],
  "annotationsCount": 1,
  "annotated": true
}