{
  "id": "6775455ce2d1e34dcb8dd461",
  "datasetId": "67753ec471a6654d3f980dab",
  "url": "https://rc-gate.dataloop.ai/api/v1/items/6775455ce2d1e34dcb8dd461",
  "dataset": "https://rc-gate.dataloop.ai/api/v1/datasets/67753ec471a6654d3f980dab",
  "createdAt": "2025-01-01T13:38:36.358Z",
  "dir": "/",
  "filename": "/35401.json",
  "type": "file",
  "hidden": false,
  "metadata": {
    "system": {
      "encoding": "7bit",
      "isBinary": false,
      "mimetype": "application/json",
      "originalname": "35401.json",
      "refs": [],
      "shebang": {
        "dltype": "prompt"
      },
      "size": 240,
      "tags": {
        "train": true
      },
      "taskStatusLog": []
    }
  },
  "name": "35401.json",
  "creator": "yaya.t@dataloop.ai",
  "updatedAt": "2025-01-02T05:02:42.065Z",
  "updatedBy": "rubiks@dataloop.ai",
  "stream": "https://rc-gate.dataloop.ai/api/v1/items/6775455ce2d1e34dcb8dd461/stream",
  "thumbnail": "https://rc-gate.dataloop.ai/api/v1/items/6775455ce2d1e34dcb8dd461/thumbnail",
  "annotations": [
    {
      "id": "6775a2eb0d0617c45b6e8375",
      "datasetId": "67753ec471a6654d3f980dab",
      "itemId": "6775455ce2d1e34dcb8dd461",
      "url": "https://rc-gate.dataloop.ai/api/v1/annotations/6775a2eb0d0617c45b6e8375",
      "item": "https://rc-gate.dataloop.ai/api/v1/items/6775455ce2d1e34dcb8dd461",
      "dataset": "https://rc-gate.dataloop.ai/api/v1/datasets/67753ec471a6654d3f980dab",
      "type": "text",
      "label": "free-text",
      "coordinates": "This is a photo of Shoes from Men's Footwear",
      "metadata": {
        "system": {
          "automated": true,
          "promptId": "1"
        },
        "user": {}
      },
      "creator": "yaya.t@dataloop.ai",
      "createdAt": "2025-01-01T20:17:47.886Z",
      "updatedBy": "yaya.t@dataloop.ai",
      "updatedAt": "2025-01-01T20:17:47.886Z",
      "hash": "6d34bb0d9f49acda1ac744c6da517d7b96f1eca8",
      "source": "sdk"
    }
  ],
  "annotationsCount": 1,
  "annotated": true
}