{
  "id": "677551fc5cdbbed0ecdd496e",
  "datasetId": "67753ec471a6654d3f980dab",
  "url": "https://rc-gate.dataloop.ai/api/v1/items/677551fc5cdbbed0ecdd496e",
  "dataset": "https://rc-gate.dataloop.ai/api/v1/datasets/67753ec471a6654d3f980dab",
  "createdAt": "2025-01-01T14:32:28.358Z",
  "dir": "/",
  "filename": "/43543.json",
  "type": "file",
  "hidden": false,
  "metadata": {
    "system": {
      "encoding": "7bit",
      "isBinary": false,
      "mimetype": "application/json",
      "originalname": "43543.json",
      "refs": [],
      "shebang": {
        "dltype": "prompt"
      },
      "size": 240,
      "tags": {
        "train": true
      },
      "taskStatusLog": []
    }
  },
  "name": "43543.json",
  "creator": "yaya.t@dataloop.ai",
  "updatedAt": "2025-01-02T05:02:40.914Z",
  "updatedBy": "rubiks@dataloop.ai",
  "stream": "https://rc-gate.dataloop.ai/api/v1/items/677551fc5cdbbed0ecdd496e/stream",
  "thumbnail": "https://rc-gate.dataloop.ai/api/v1/items/677551fc5cdbbed0ecdd496e/thumbnail",
  "annotations": [
    {
      "id": "6775b8770d0617470e6f00e1",
      "datasetId": "67753ec471a6654d3f980dab",
      "itemId": "677551fc5cdbbed0ecdd496e",
      "url": "https://rc-gate.dataloop.ai/api/v1/annotations/6775b8770d0617470e6f00e1",
      "item": "https://rc-gate.dataloop.ai/api/v1/items/677551fc5cdbbed0ecdd496e",
      "dataset": "https://rc-gate.dataloop.ai/api/v1/datasets/67753ec471a6654d3f980dab",
      "type": "text",
      "label": "free-text",
      "coordinates": "This is a photo of Topwear from Men's Apparel",
      "metadata": {
        "system": {
          "automated": true,
          "promptId": "1"
        },
        "user": {}
      },
      "creator": "yaya.t@dataloop.ai",
      "createdAt": "2025-01-01T21:49:43.122Z",
      "updatedBy": "yaya.t@dataloop.ai",
      "updatedAt": "2025-01-01T21:49:43.122Z",
      "hash": "16bd5e90a9cd979c873324e1837941720debe0a2",
      "source": "sdk"
    }
  ],
  "annotationsCount": 1,
  "annotated": true
}