{
  "id": "67754b43571407281bc4f08a",
  "datasetId": "67753ec471a6654d3f980dab",
  "url": "https://rc-gate.dataloop.ai/api/v1/items/67754b43571407281bc4f08a",
  "dataset": "https://rc-gate.dataloop.ai/api/v1/datasets/67753ec471a6654d3f980dab",
  "createdAt": "2025-01-01T14:03:46.954Z",
  "dir": "/",
  "filename": "/4581.json",
  "type": "file",
  "hidden": false,
  "metadata": {
    "system": {
      "encoding": "7bit",
      "isBinary": false,
      "mimetype": "application/json",
      "originalname": "4581.json",
      "refs": [],
      "shebang": {
        "dltype": "prompt"
      },
      "size": 240,
      "tags": {
        "train": true
      },
      "taskStatusLog": []
    }
  },
  "name": "4581.json",
  "creator": "yaya.t@dataloop.ai",
  "updatedAt": "2025-01-02T05:02:40.525Z",
  "updatedBy": "rubiks@dataloop.ai",
  "stream": "https://rc-gate.dataloop.ai/api/v1/items/67754b43571407281bc4f08a/stream",
  "thumbnail": "https://rc-gate.dataloop.ai/api/v1/items/67754b43571407281bc4f08a/thumbnail",
  "annotations": [
    {
      "id": "6775b4ef0d061774476ec490",
      "datasetId": "67753ec471a6654d3f980dab",
      "itemId": "67754b43571407281bc4f08a",
      "url": "https://rc-gate.dataloop.ai/api/v1/annotations/6775b4ef0d061774476ec490",
      "item": "https://rc-gate.dataloop.ai/api/v1/items/67754b43571407281bc4f08a",
      "dataset": "https://rc-gate.dataloop.ai/api/v1/datasets/67753ec471a6654d3f980dab",
      "type": "text",
      "label": "free-text",
      "coordinates": "This is a photo of Topwear from Women's Apparel",
      "metadata": {
        "system": {
          "automated": true,
          "promptId": "1"
        },
        "user": {}
      },
      "creator": "yaya.t@dataloop.ai",
      "createdAt": "2025-01-01T21:34:39.699Z",
      "updatedBy": "yaya.t@dataloop.ai",
      "updatedAt": "2025-01-01T21:34:39.699Z",
      "hash": "651378e154f852d11f37b424806e8c9aff1c8d47",
      "source": "sdk"
    }
  ],
  "annotationsCount": 1,
  "annotated": true
}