{
  "id": "67754db65714073b07c52a0d",
  "datasetId": "67753ec471a6654d3f980dab",
  "url": "https://rc-gate.dataloop.ai/api/v1/items/67754db65714073b07c52a0d",
  "dataset": "https://rc-gate.dataloop.ai/api/v1/datasets/67753ec471a6654d3f980dab",
  "createdAt": "2025-01-01T14:14:14.565Z",
  "dir": "/",
  "filename": "/55565.json",
  "type": "file",
  "hidden": false,
  "metadata": {
    "system": {
      "encoding": "7bit",
      "isBinary": false,
      "mimetype": "application/json",
      "originalname": "55565.json",
      "refs": [],
      "shebang": {
        "dltype": "prompt"
      },
      "size": 240,
      "tags": {
        "train": true
      },
      "taskStatusLog": []
    }
  },
  "name": "55565.json",
  "creator": "yaya.t@dataloop.ai",
  "updatedAt": "2025-01-02T05:02:41.577Z",
  "updatedBy": "rubiks@dataloop.ai",
  "stream": "https://rc-gate.dataloop.ai/api/v1/items/67754db65714073b07c52a0d/stream",
  "thumbnail": "https://rc-gate.dataloop.ai/api/v1/items/67754db65714073b07c52a0d/thumbnail",
  "annotations": [
    {
      "id": "6775b631a531013b7e0c6d1c",
      "datasetId": "67753ec471a6654d3f980dab",
      "itemId": "67754db65714073b07c52a0d",
      "url": "https://rc-gate.dataloop.ai/api/v1/annotations/6775b631a531013b7e0c6d1c",
      "item": "https://rc-gate.dataloop.ai/api/v1/items/67754db65714073b07c52a0d",
      "dataset": "https://rc-gate.dataloop.ai/api/v1/datasets/67753ec471a6654d3f980dab",
      "type": "text",
      "label": "free-text",
      "coordinates": "This is a photo of Fragrance from Women's Personal Care",
      "metadata": {
        "system": {
          "automated": true,
          "promptId": "1"
        },
        "user": {}
      },
      "creator": "yaya.t@dataloop.ai",
      "createdAt": "2025-01-01T21:40:01.959Z",
      "updatedBy": "yaya.t@dataloop.ai",
      "updatedAt": "2025-01-01T21:40:01.959Z",
      "hash": "8557fc52ee9721f02aaab51e46e0a44c1ab36716",
      "source": "sdk"
    }
  ],
  "annotationsCount": 1,
  "annotated": true
}