{
  "id": "677549ac04951e974180135e",
  "datasetId": "67753ec471a6654d3f980dab",
  "url": "https://rc-gate.dataloop.ai/api/v1/items/677549ac04951e974180135e",
  "dataset": "https://rc-gate.dataloop.ai/api/v1/datasets/67753ec471a6654d3f980dab",
  "createdAt": "2025-01-01T13:57:00.550Z",
  "dir": "/",
  "filename": "/8556.json",
  "type": "file",
  "hidden": false,
  "metadata": {
    "system": {
      "encoding": "7bit",
      "isBinary": false,
      "mimetype": "application/json",
      "originalname": "8556.json",
      "refs": [],
      "shebang": {
        "dltype": "prompt"
      },
      "size": 240,
      "tags": {
        "train": true
      },
      "taskStatusLog": []
    }
  },
  "name": "8556.json",
  "creator": "yaya.t@dataloop.ai",
  "updatedAt": "2025-01-02T05:02:42.071Z",
  "updatedBy": "rubiks@dataloop.ai",
  "stream": "https://rc-gate.dataloop.ai/api/v1/items/677549ac04951e974180135e/stream",
  "thumbnail": "https://rc-gate.dataloop.ai/api/v1/items/677549ac04951e974180135e/thumbnail",
  "annotations": [
    {
      "id": "6775b4560d06175d086eba6a",
      "datasetId": "67753ec471a6654d3f980dab",
      "itemId": "677549ac04951e974180135e",
      "url": "https://rc-gate.dataloop.ai/api/v1/annotations/6775b4560d06175d086eba6a",
      "item": "https://rc-gate.dataloop.ai/api/v1/items/677549ac04951e974180135e",
      "dataset": "https://rc-gate.dataloop.ai/api/v1/datasets/67753ec471a6654d3f980dab",
      "type": "text",
      "label": "free-text",
      "coordinates": "This is a photo of Topwear from Men's Apparel",
      "metadata": {
        "system": {
          "automated": true,
          "promptId": "1"
        },
        "user": {}
      },
      "creator": "yaya.t@dataloop.ai",
      "createdAt": "2025-01-01T21:32:06.066Z",
      "updatedBy": "yaya.t@dataloop.ai",
      "updatedAt": "2025-01-01T21:32:06.066Z",
      "hash": "1e9edb9778a52aa1a3c7bf2f3a1a32b82e34fae8",
      "source": "sdk"
    }
  ],
  "annotationsCount": 1,
  "annotated": true
}