{
  "id": "6775428b68373f49457f6d0f",
  "datasetId": "67753ec471a6654d3f980dab",
  "url": "https://rc-gate.dataloop.ai/api/v1/items/6775428b68373f49457f6d0f",
  "dataset": "https://rc-gate.dataloop.ai/api/v1/datasets/67753ec471a6654d3f980dab",
  "createdAt": "2025-01-01T13:26:35.910Z",
  "dir": "/",
  "filename": "/8948.json",
  "type": "file",
  "hidden": false,
  "metadata": {
    "system": {
      "encoding": "7bit",
      "isBinary": false,
      "mimetype": "application/json",
      "originalname": "8948.json",
      "refs": [],
      "shebang": {
        "dltype": "prompt"
      },
      "size": 240,
      "tags": {
        "train": true
      },
      "taskStatusLog": []
    }
  },
  "name": "8948.json",
  "creator": "yaya.t@dataloop.ai",
  "updatedAt": "2025-01-02T05:02:41.079Z",
  "updatedBy": "rubiks@dataloop.ai",
  "stream": "https://rc-gate.dataloop.ai/api/v1/items/6775428b68373f49457f6d0f/stream",
  "thumbnail": "https://rc-gate.dataloop.ai/api/v1/items/6775428b68373f49457f6d0f/thumbnail",
  "annotations": [
    {
      "id": "6775a29283871c375506a748",
      "datasetId": "67753ec471a6654d3f980dab",
      "itemId": "6775428b68373f49457f6d0f",
      "url": "https://rc-gate.dataloop.ai/api/v1/annotations/6775a29283871c375506a748",
      "item": "https://rc-gate.dataloop.ai/api/v1/items/6775428b68373f49457f6d0f",
      "dataset": "https://rc-gate.dataloop.ai/api/v1/datasets/67753ec471a6654d3f980dab",
      "type": "text",
      "label": "free-text",
      "coordinates": "This is a photo of Bottomwear from Men's Apparel",
      "metadata": {
        "system": {
          "automated": true,
          "promptId": "1"
        },
        "user": {}
      },
      "creator": "yaya.t@dataloop.ai",
      "createdAt": "2025-01-01T20:16:18.859Z",
      "updatedBy": "yaya.t@dataloop.ai",
      "updatedAt": "2025-01-01T20:16:18.859Z",
      "hash": "2eab348fdb5c330d77179a94651458576149b3bc",
      "source": "sdk"
    }
  ],
  "annotationsCount": 1,
  "annotated": true
}