{
  "id": "6775503be2d1e332ef8edbd7",
  "datasetId": "67753ec471a6654d3f980dab",
  "url": "https://rc-gate.dataloop.ai/api/v1/items/6775503be2d1e332ef8edbd7",
  "dataset": "https://rc-gate.dataloop.ai/api/v1/datasets/67753ec471a6654d3f980dab",
  "createdAt": "2025-01-01T14:24:59.440Z",
  "dir": "/",
  "filename": "/10704.json",
  "type": "file",
  "hidden": false,
  "metadata": {
    "system": {
      "encoding": "7bit",
      "isBinary": false,
      "mimetype": "application/json",
      "originalname": "10704.json",
      "refs": [],
      "shebang": {
        "dltype": "prompt"
      },
      "size": 240,
      "tags": {
        "train": true
      },
      "taskStatusLog": []
    }
  },
  "name": "10704.json",
  "creator": "yaya.t@dataloop.ai",
  "updatedAt": "2025-01-02T05:02:40.510Z",
  "updatedBy": "rubiks@dataloop.ai",
  "stream": "https://rc-gate.dataloop.ai/api/v1/items/6775503be2d1e332ef8edbd7/stream",
  "thumbnail": "https://rc-gate.dataloop.ai/api/v1/items/6775503be2d1e332ef8edbd7/thumbnail",
  "annotations": [
    {
      "id": "6775b79ba5310169f70c85f4",
      "datasetId": "67753ec471a6654d3f980dab",
      "itemId": "6775503be2d1e332ef8edbd7",
      "url": "https://rc-gate.dataloop.ai/api/v1/annotations/6775b79ba5310169f70c85f4",
      "item": "https://rc-gate.dataloop.ai/api/v1/items/6775503be2d1e332ef8edbd7",
      "dataset": "https://rc-gate.dataloop.ai/api/v1/datasets/67753ec471a6654d3f980dab",
      "type": "text",
      "label": "free-text",
      "coordinates": "This is a photo of Watches from Women's Accessories",
      "metadata": {
        "system": {
          "automated": true,
          "promptId": "1"
        },
        "user": {}
      },
      "creator": "yaya.t@dataloop.ai",
      "createdAt": "2025-01-01T21:46:03.073Z",
      "updatedBy": "yaya.t@dataloop.ai",
      "updatedAt": "2025-01-01T21:46:03.073Z",
      "hash": "64a071d0a2ba1fa77089f80d9e2029b834f31684",
      "source": "sdk"
    }
  ],
  "annotationsCount": 1,
  "annotated": true
}