{
  "id": "67754697e2d1e3ca0e8deef3",
  "datasetId": "67753ec471a6654d3f980dab",
  "url": "https://rc-gate.dataloop.ai/api/v1/items/67754697e2d1e3ca0e8deef3",
  "dataset": "https://rc-gate.dataloop.ai/api/v1/datasets/67753ec471a6654d3f980dab",
  "createdAt": "2025-01-01T13:43:51.558Z",
  "dir": "/",
  "filename": "/13943.json",
  "type": "file",
  "hidden": false,
  "metadata": {
    "system": {
      "encoding": "7bit",
      "isBinary": false,
      "mimetype": "application/json",
      "originalname": "13943.json",
      "refs": [],
      "shebang": {
        "dltype": "prompt"
      },
      "size": 240,
      "tags": {
        "train": true
      },
      "taskStatusLog": []
    }
  },
  "name": "13943.json",
  "creator": "yaya.t@dataloop.ai",
  "updatedAt": "2025-01-02T05:02:40.514Z",
  "updatedBy": "rubiks@dataloop.ai",
  "stream": "https://rc-gate.dataloop.ai/api/v1/items/67754697e2d1e3ca0e8deef3/stream",
  "thumbnail": "https://rc-gate.dataloop.ai/api/v1/items/67754697e2d1e3ca0e8deef3/thumbnail",
  "annotations": [
    {
      "id": "6775a406a53101477d0c2542",
      "datasetId": "67753ec471a6654d3f980dab",
      "itemId": "67754697e2d1e3ca0e8deef3",
      "url": "https://rc-gate.dataloop.ai/api/v1/annotations/6775a406a53101477d0c2542",
      "item": "https://rc-gate.dataloop.ai/api/v1/items/67754697e2d1e3ca0e8deef3",
      "dataset": "https://rc-gate.dataloop.ai/api/v1/datasets/67753ec471a6654d3f980dab",
      "type": "text",
      "label": "free-text",
      "coordinates": "This is a photo of Topwear from Men's Apparel",
      "metadata": {
        "system": {
          "automated": true,
          "promptId": "1"
        },
        "user": {}
      },
      "creator": "yaya.t@dataloop.ai",
      "createdAt": "2025-01-01T20:22:30.674Z",
      "updatedBy": "yaya.t@dataloop.ai",
      "updatedAt": "2025-01-01T20:22:30.674Z",
      "hash": "126a01a3543f0ff888226e5e94b3045b4f6ce401",
      "source": "sdk"
    }
  ],
  "annotationsCount": 1,
  "annotated": true
}