{
  "id": "677542d104951e03737f6b1e",
  "datasetId": "67753ec471a6654d3f980dab",
  "url": "https://rc-gate.dataloop.ai/api/v1/items/677542d104951e03737f6b1e",
  "dataset": "https://rc-gate.dataloop.ai/api/v1/datasets/67753ec471a6654d3f980dab",
  "createdAt": "2025-01-01T13:27:45.830Z",
  "dir": "/",
  "filename": "/13961.json",
  "type": "file",
  "hidden": false,
  "metadata": {
    "system": {
      "encoding": "7bit",
      "isBinary": false,
      "mimetype": "application/json",
      "originalname": "13961.json",
      "refs": [],
      "shebang": {
        "dltype": "prompt"
      },
      "size": 240,
      "tags": {
        "train": true
      },
      "taskStatusLog": []
    }
  },
  "name": "13961.json",
  "creator": "yaya.t@dataloop.ai",
  "updatedAt": "2025-01-02T05:02:40.514Z",
  "updatedBy": "rubiks@dataloop.ai",
  "stream": "https://rc-gate.dataloop.ai/api/v1/items/677542d104951e03737f6b1e/stream",
  "thumbnail": "https://rc-gate.dataloop.ai/api/v1/items/677542d104951e03737f6b1e/thumbnail",
  "annotations": [
    {
      "id": "6775a1a2a53101a19c0c009a",
      "datasetId": "67753ec471a6654d3f980dab",
      "itemId": "677542d104951e03737f6b1e",
      "url": "https://rc-gate.dataloop.ai/api/v1/annotations/6775a1a2a53101a19c0c009a",
      "item": "https://rc-gate.dataloop.ai/api/v1/items/677542d104951e03737f6b1e",
      "dataset": "https://rc-gate.dataloop.ai/api/v1/datasets/67753ec471a6654d3f980dab",
      "type": "text",
      "label": "free-text",
      "coordinates": "This is a photo of Topwear from Women's Apparel",
      "metadata": {
        "system": {
          "automated": true,
          "promptId": "1"
        },
        "user": {}
      },
      "creator": "yaya.t@dataloop.ai",
      "createdAt": "2025-01-01T20:12:18.967Z",
      "updatedBy": "yaya.t@dataloop.ai",
      "updatedAt": "2025-01-01T20:12:18.967Z",
      "hash": "3db5c5e40905753713bd14e236d31eb741df18cf",
      "source": "sdk"
    }
  ],
  "annotationsCount": 1,
  "annotated": true
}