{
  "id": "677550d5de27a2642573959b",
  "datasetId": "67753ec471a6654d3f980dab",
  "url": "https://rc-gate.dataloop.ai/api/v1/items/677550d5de27a2642573959b",
  "dataset": "https://rc-gate.dataloop.ai/api/v1/datasets/67753ec471a6654d3f980dab",
  "createdAt": "2025-01-01T14:27:33.867Z",
  "dir": "/",
  "filename": "/16970.json",
  "type": "file",
  "hidden": false,
  "metadata": {
    "system": {
      "encoding": "7bit",
      "isBinary": false,
      "mimetype": "application/json",
      "originalname": "16970.json",
      "refs": [],
      "shebang": {
        "dltype": "prompt"
      },
      "size": 240,
      "tags": {
        "train": true
      },
      "taskStatusLog": []
    }
  },
  "name": "16970.json",
  "creator": "yaya.t@dataloop.ai",
  "updatedAt": "2025-01-02T05:02:41.476Z",
  "updatedBy": "rubiks@dataloop.ai",
  "stream": "https://rc-gate.dataloop.ai/api/v1/items/677550d5de27a2642573959b/stream",
  "thumbnail": "https://rc-gate.dataloop.ai/api/v1/items/677550d5de27a2642573959b/thumbnail",
  "annotations": [
    {
      "id": "6775b853a5310130bd0c9218",
      "datasetId": "67753ec471a6654d3f980dab",
      "itemId": "677550d5de27a2642573959b",
      "url": "https://rc-gate.dataloop.ai/api/v1/annotations/6775b853a5310130bd0c9218",
      "item": "https://rc-gate.dataloop.ai/api/v1/items/677550d5de27a2642573959b",
      "dataset": "https://rc-gate.dataloop.ai/api/v1/datasets/67753ec471a6654d3f980dab",
      "type": "text",
      "label": "free-text",
      "coordinates": "This is a photo of Sandal from Men's Footwear",
      "metadata": {
        "system": {
          "automated": true,
          "promptId": "1"
        },
        "user": {}
      },
      "creator": "yaya.t@dataloop.ai",
      "createdAt": "2025-01-01T21:49:07.254Z",
      "updatedBy": "yaya.t@dataloop.ai",
      "updatedAt": "2025-01-01T21:49:07.254Z",
      "hash": "43ddd1a962936cbecaed74a70f70c111dbda2913",
      "source": "sdk"
    }
  ],
  "annotationsCount": 1,
  "annotated": true
}