{
  "id": "677551c604951e2fc680d6a6",
  "datasetId": "67753ec471a6654d3f980dab",
  "url": "https://rc-gate.dataloop.ai/api/v1/items/677551c604951e2fc680d6a6",
  "dataset": "https://rc-gate.dataloop.ai/api/v1/datasets/67753ec471a6654d3f980dab",
  "createdAt": "2025-01-01T14:31:34.620Z",
  "dir": "/",
  "filename": "/21934.json",
  "type": "file",
  "hidden": false,
  "metadata": {
    "system": {
      "encoding": "7bit",
      "isBinary": false,
      "mimetype": "application/json",
      "originalname": "21934.json",
      "refs": [],
      "shebang": {
        "dltype": "prompt"
      },
      "size": 240,
      "tags": {
        "train": true
      },
      "taskStatusLog": []
    }
  },
  "name": "21934.json",
  "creator": "yaya.t@dataloop.ai",
  "updatedAt": "2025-01-02T05:02:41.574Z",
  "updatedBy": "rubiks@dataloop.ai",
  "stream": "https://rc-gate.dataloop.ai/api/v1/items/677551c604951e2fc680d6a6/stream",
  "thumbnail": "https://rc-gate.dataloop.ai/api/v1/items/677551c604951e2fc680d6a6/thumbnail",
  "annotations": [
    {
      "id": "6775b8ec83871c326407330b",
      "datasetId": "67753ec471a6654d3f980dab",
      "itemId": "677551c604951e2fc680d6a6",
      "url": "https://rc-gate.dataloop.ai/api/v1/annotations/6775b8ec83871c326407330b",
      "item": "https://rc-gate.dataloop.ai/api/v1/items/677551c604951e2fc680d6a6",
      "dataset": "https://rc-gate.dataloop.ai/api/v1/datasets/67753ec471a6654d3f980dab",
      "type": "text",
      "label": "free-text",
      "coordinates": "This is a photo of Bags from Women's Accessories",
      "metadata": {
        "system": {
          "automated": true,
          "promptId": "1"
        },
        "user": {}
      },
      "creator": "yaya.t@dataloop.ai",
      "createdAt": "2025-01-01T21:51:40.192Z",
      "updatedBy": "yaya.t@dataloop.ai",
      "updatedAt": "2025-01-01T21:51:40.192Z",
      "hash": "168af8bc5c30b54a17af138343979ccec43b16da",
      "source": "sdk"
    }
  ],
  "annotationsCount": 1,
  "annotated": true
}