{
  "id": "67754f7004951efea88095da",
  "datasetId": "67753ec471a6654d3f980dab",
  "url": "https://rc-gate.dataloop.ai/api/v1/items/67754f7004951efea88095da",
  "dataset": "https://rc-gate.dataloop.ai/api/v1/datasets/67753ec471a6654d3f980dab",
  "createdAt": "2025-01-01T14:21:36.461Z",
  "dir": "/",
  "filename": "/22036.json",
  "type": "file",
  "hidden": false,
  "metadata": {
    "system": {
      "encoding": "7bit",
      "isBinary": false,
      "mimetype": "application/json",
      "originalname": "22036.json",
      "refs": [],
      "shebang": {
        "dltype": "prompt"
      },
      "size": 240,
      "tags": {
        "train": true
      },
      "taskStatusLog": []
    }
  },
  "name": "22036.json",
  "creator": "yaya.t@dataloop.ai",
  "updatedAt": "2025-01-02T05:02:42.071Z",
  "updatedBy": "rubiks@dataloop.ai",
  "stream": "https://rc-gate.dataloop.ai/api/v1/items/67754f7004951efea88095da/stream",
  "thumbnail": "https://rc-gate.dataloop.ai/api/v1/items/67754f7004951efea88095da/thumbnail",
  "annotations": [
    {
      "id": "6775b7180d0617166d6ee95c",
      "datasetId": "67753ec471a6654d3f980dab",
      "itemId": "67754f7004951efea88095da",
      "url": "https://rc-gate.dataloop.ai/api/v1/annotations/6775b7180d0617166d6ee95c",
      "item": "https://rc-gate.dataloop.ai/api/v1/items/67754f7004951efea88095da",
      "dataset": "https://rc-gate.dataloop.ai/api/v1/datasets/67753ec471a6654d3f980dab",
      "type": "text",
      "label": "free-text",
      "coordinates": "This is a photo of Topwear from Women's Apparel",
      "metadata": {
        "system": {
          "automated": true,
          "promptId": "1"
        },
        "user": {}
      },
      "creator": "yaya.t@dataloop.ai",
      "createdAt": "2025-01-01T21:43:52.727Z",
      "updatedBy": "yaya.t@dataloop.ai",
      "updatedAt": "2025-01-01T21:43:52.727Z",
      "hash": "33dd434abb7702be0d835c614275dc63a7c18362",
      "source": "sdk"
    }
  ],
  "annotationsCount": 1,
  "annotated": true
}