{
  "id": "6775499004951e185280114c",
  "datasetId": "67753ec471a6654d3f980dab",
  "url": "https://rc-gate.dataloop.ai/api/v1/items/6775499004951e185280114c",
  "dataset": "https://rc-gate.dataloop.ai/api/v1/datasets/67753ec471a6654d3f980dab",
  "createdAt": "2025-01-01T13:56:32.639Z",
  "dir": "/",
  "filename": "/24618.json",
  "type": "file",
  "hidden": false,
  "metadata": {
    "system": {
      "encoding": "7bit",
      "isBinary": false,
      "mimetype": "application/json",
      "originalname": "24618.json",
      "refs": [],
      "shebang": {
        "dltype": "prompt"
      },
      "size": 240,
      "tags": {
        "train": true
      },
      "taskStatusLog": []
    }
  },
  "name": "24618.json",
  "creator": "yaya.t@dataloop.ai",
  "updatedAt": "2025-01-02T05:02:41.248Z",
  "updatedBy": "rubiks@dataloop.ai",
  "stream": "https://rc-gate.dataloop.ai/api/v1/items/6775499004951e185280114c/stream",
  "thumbnail": "https://rc-gate.dataloop.ai/api/v1/items/6775499004951e185280114c/thumbnail",
  "annotations": [
    {
      "id": "6775b44aa531017bac0c4d67",
      "datasetId": "67753ec471a6654d3f980dab",
      "itemId": "6775499004951e185280114c",
      "url": "https://rc-gate.dataloop.ai/api/v1/annotations/6775b44aa531017bac0c4d67",
      "item": "https://rc-gate.dataloop.ai/api/v1/items/6775499004951e185280114c",
      "dataset": "https://rc-gate.dataloop.ai/api/v1/datasets/67753ec471a6654d3f980dab",
      "type": "text",
      "label": "free-text",
      "coordinates": "This is a photo of Wallets from Men's Accessories",
      "metadata": {
        "system": {
          "automated": true,
          "promptId": "1"
        },
        "user": {}
      },
      "creator": "yaya.t@dataloop.ai",
      "createdAt": "2025-01-01T21:31:54.503Z",
      "updatedBy": "yaya.t@dataloop.ai",
      "updatedAt": "2025-01-01T21:31:54.503Z",
      "hash": "79b9c79e39e784fff7569d29d4432cdc55ea66e8",
      "source": "sdk"
    }
  ],
  "annotationsCount": 1,
  "annotated": true
}