{
  "id": "677547d404951e837c7fe243",
  "datasetId": "67753ec471a6654d3f980dab",
  "url": "https://rc-gate.dataloop.ai/api/v1/items/677547d404951e837c7fe243",
  "dataset": "https://rc-gate.dataloop.ai/api/v1/datasets/67753ec471a6654d3f980dab",
  "createdAt": "2025-01-01T13:49:08.229Z",
  "dir": "/",
  "filename": "/29676.json",
  "type": "file",
  "hidden": false,
  "metadata": {
    "system": {
      "encoding": "7bit",
      "isBinary": false,
      "mimetype": "application/json",
      "originalname": "29676.json",
      "refs": [],
      "shebang": {
        "dltype": "prompt"
      },
      "size": 240,
      "tags": {
        "train": true
      },
      "taskStatusLog": []
    }
  },
  "name": "29676.json",
  "creator": "yaya.t@dataloop.ai",
  "updatedAt": "2025-01-02T05:02:40.529Z",
  "updatedBy": "rubiks@dataloop.ai",
  "stream": "https://rc-gate.dataloop.ai/api/v1/items/677547d404951e837c7fe243/stream",
  "thumbnail": "https://rc-gate.dataloop.ai/api/v1/items/677547d404951e837c7fe243/thumbnail",
  "annotations": [
    {
      "id": "6775a41b83871c027306bd59",
      "datasetId": "67753ec471a6654d3f980dab",
      "itemId": "677547d404951e837c7fe243",
      "url": "https://rc-gate.dataloop.ai/api/v1/annotations/6775a41b83871c027306bd59",
      "item": "https://rc-gate.dataloop.ai/api/v1/items/677547d404951e837c7fe243",
      "dataset": "https://rc-gate.dataloop.ai/api/v1/datasets/67753ec471a6654d3f980dab",
      "type": "text",
      "label": "free-text",
      "coordinates": "This is a photo of Bottomwear from Men's Apparel",
      "metadata": {
        "system": {
          "automated": true,
          "promptId": "1"
        },
        "user": {}
      },
      "creator": "yaya.t@dataloop.ai",
      "createdAt": "2025-01-01T20:22:51.928Z",
      "updatedBy": "yaya.t@dataloop.ai",
      "updatedAt": "2025-01-01T20:22:51.928Z",
      "hash": "8089fe111b61ecb1848ed5758566087c8fed4bc8",
      "source": "sdk"
    }
  ],
  "annotationsCount": 1,
  "annotated": true
}