{
  "id": "67754cc1e2d1e375a98e8593",
  "datasetId": "67753ec471a6654d3f980dab",
  "url": "https://rc-gate.dataloop.ai/api/v1/items/67754cc1e2d1e375a98e8593",
  "dataset": "https://rc-gate.dataloop.ai/api/v1/datasets/67753ec471a6654d3f980dab",
  "createdAt": "2025-01-01T14:10:09.907Z",
  "dir": "/",
  "filename": "/33192.json",
  "type": "file",
  "hidden": false,
  "metadata": {
    "system": {
      "encoding": "7bit",
      "isBinary": false,
      "mimetype": "application/json",
      "originalname": "33192.json",
      "refs": [],
      "shebang": {
        "dltype": "prompt"
      },
      "size": 240,
      "tags": {
        "train": true
      },
      "taskStatusLog": []
    }
  },
  "name": "33192.json",
  "creator": "yaya.t@dataloop.ai",
  "updatedAt": "2025-01-02T05:02:40.529Z",
  "updatedBy": "rubiks@dataloop.ai",
  "stream": "https://rc-gate.dataloop.ai/api/v1/items/67754cc1e2d1e375a98e8593/stream",
  "thumbnail": "https://rc-gate.dataloop.ai/api/v1/items/67754cc1e2d1e375a98e8593/thumbnail",
  "annotations": [
    {
      "id": "6775b5ce83871c17ee06fd5c",
      "datasetId": "67753ec471a6654d3f980dab",
      "itemId": "67754cc1e2d1e375a98e8593",
      "url": "https://rc-gate.dataloop.ai/api/v1/annotations/6775b5ce83871c17ee06fd5c",
      "item": "https://rc-gate.dataloop.ai/api/v1/items/67754cc1e2d1e375a98e8593",
      "dataset": "https://rc-gate.dataloop.ai/api/v1/datasets/67753ec471a6654d3f980dab",
      "type": "text",
      "label": "free-text",
      "coordinates": "This is a photo of Topwear from Women's Apparel",
      "metadata": {
        "system": {
          "automated": true,
          "promptId": "1"
        },
        "user": {}
      },
      "creator": "yaya.t@dataloop.ai",
      "createdAt": "2025-01-01T21:38:22.033Z",
      "updatedBy": "yaya.t@dataloop.ai",
      "updatedAt": "2025-01-01T21:38:22.033Z",
      "hash": "bdbed1602cd28182f14f6523c8cfc5e3a75ab558",
      "source": "sdk"
    }
  ],
  "annotationsCount": 1,
  "annotated": true
}