{
  "id": "67754db9e2d1e31c4b8e9b75",
  "datasetId": "67753ec471a6654d3f980dab",
  "url": "https://rc-gate.dataloop.ai/api/v1/items/67754db9e2d1e31c4b8e9b75",
  "dataset": "https://rc-gate.dataloop.ai/api/v1/datasets/67753ec471a6654d3f980dab",
  "createdAt": "2025-01-01T14:14:17.570Z",
  "dir": "/",
  "filename": "/34599.json",
  "type": "file",
  "hidden": false,
  "metadata": {
    "system": {
      "encoding": "7bit",
      "isBinary": false,
      "mimetype": "application/json",
      "originalname": "34599.json",
      "refs": [],
      "shebang": {
        "dltype": "prompt"
      },
      "size": 240,
      "tags": {
        "train": true
      },
      "taskStatusLog": []
    }
  },
  "name": "34599.json",
  "creator": "yaya.t@dataloop.ai",
  "updatedAt": "2025-01-02T05:02:42.036Z",
  "updatedBy": "rubiks@dataloop.ai",
  "stream": "https://rc-gate.dataloop.ai/api/v1/items/67754db9e2d1e31c4b8e9b75/stream",
  "thumbnail": "https://rc-gate.dataloop.ai/api/v1/items/67754db9e2d1e31c4b8e9b75/thumbnail",
  "annotations": [
    {
      "id": "6775b6350d06176e796ed9c0",
      "datasetId": "67753ec471a6654d3f980dab",
      "itemId": "67754db9e2d1e31c4b8e9b75",
      "url": "https://rc-gate.dataloop.ai/api/v1/annotations/6775b6350d06176e796ed9c0",
      "item": "https://rc-gate.dataloop.ai/api/v1/items/67754db9e2d1e31c4b8e9b75",
      "dataset": "https://rc-gate.dataloop.ai/api/v1/datasets/67753ec471a6654d3f980dab",
      "type": "text",
      "label": "free-text",
      "coordinates": "This is a photo of Dress from Women's Apparel",
      "metadata": {
        "system": {
          "automated": true,
          "promptId": "1"
        },
        "user": {}
      },
      "creator": "yaya.t@dataloop.ai",
      "createdAt": "2025-01-01T21:40:05.385Z",
      "updatedBy": "yaya.t@dataloop.ai",
      "updatedAt": "2025-01-01T21:40:05.385Z",
      "hash": "b9b0fc2a840ed3cc0fe15b772a354cb119fe41ed",
      "source": "sdk"
    }
  ],
  "annotationsCount": 1,
  "annotated": true
}