{
  "id": "6775442f04951e6f877f8a54",
  "datasetId": "67753ec471a6654d3f980dab",
  "url": "https://rc-gate.dataloop.ai/api/v1/items/6775442f04951e6f877f8a54",
  "dataset": "https://rc-gate.dataloop.ai/api/v1/datasets/67753ec471a6654d3f980dab",
  "createdAt": "2025-01-01T13:33:35.463Z",
  "dir": "/",
  "filename": "/40409.json",
  "type": "file",
  "hidden": false,
  "metadata": {
    "system": {
      "encoding": "7bit",
      "isBinary": false,
      "mimetype": "application/json",
      "originalname": "40409.json",
      "refs": [],
      "shebang": {
        "dltype": "prompt"
      },
      "size": 240,
      "tags": {
        "train": true
      },
      "taskStatusLog": []
    }
  },
  "name": "40409.json",
  "creator": "yaya.t@dataloop.ai",
  "updatedAt": "2025-01-02T05:02:40.529Z",
  "updatedBy": "rubiks@dataloop.ai",
  "stream": "https://rc-gate.dataloop.ai/api/v1/items/6775442f04951e6f877f8a54/stream",
  "thumbnail": "https://rc-gate.dataloop.ai/api/v1/items/6775442f04951e6f877f8a54/thumbnail",
  "annotations": [
    {
      "id": "6775a2050d06175a236e7391",
      "datasetId": "67753ec471a6654d3f980dab",
      "itemId": "6775442f04951e6f877f8a54",
      "url": "https://rc-gate.dataloop.ai/api/v1/annotations/6775a2050d06175a236e7391",
      "item": "https://rc-gate.dataloop.ai/api/v1/items/6775442f04951e6f877f8a54",
      "dataset": "https://rc-gate.dataloop.ai/api/v1/datasets/67753ec471a6654d3f980dab",
      "type": "text",
      "label": "free-text",
      "coordinates": "This is a photo of Topwear from Women's Apparel",
      "metadata": {
        "system": {
          "automated": true,
          "promptId": "1"
        },
        "user": {}
      },
      "creator": "yaya.t@dataloop.ai",
      "createdAt": "2025-01-01T20:13:57.314Z",
      "updatedBy": "yaya.t@dataloop.ai",
      "updatedAt": "2025-01-01T20:13:57.314Z",
      "hash": "1a86d9dd9b5e53d2be1bf803c6ed6e668fc36812",
      "source": "sdk"
    }
  ],
  "annotationsCount": 1,
  "annotated": true
}