{
  "id": "6775484b571407171ac4abe0",
  "datasetId": "67753ec471a6654d3f980dab",
  "url": "https://rc-gate.dataloop.ai/api/v1/items/6775484b571407171ac4abe0",
  "dataset": "https://rc-gate.dataloop.ai/api/v1/datasets/67753ec471a6654d3f980dab",
  "createdAt": "2025-01-01T13:51:07.488Z",
  "dir": "/",
  "filename": "/44906.json",
  "type": "file",
  "hidden": false,
  "metadata": {
    "system": {
      "encoding": "7bit",
      "isBinary": false,
      "mimetype": "application/json",
      "originalname": "44906.json",
      "refs": [],
      "shebang": {
        "dltype": "prompt"
      },
      "size": 240,
      "tags": {
        "train": true
      },
      "taskStatusLog": []
    }
  },
  "name": "44906.json",
  "creator": "yaya.t@dataloop.ai",
  "updatedAt": "2025-01-02T05:02:40.914Z",
  "updatedBy": "rubiks@dataloop.ai",
  "stream": "https://rc-gate.dataloop.ai/api/v1/items/6775484b571407171ac4abe0/stream",
  "thumbnail": "https://rc-gate.dataloop.ai/api/v1/items/6775484b571407171ac4abe0/thumbnail",
  "annotations": [
    {
      "id": "6775a53d83871c5e7c06d06d",
      "datasetId": "67753ec471a6654d3f980dab",
      "itemId": "6775484b571407171ac4abe0",
      "url": "https://rc-gate.dataloop.ai/api/v1/annotations/6775a53d83871c5e7c06d06d",
      "item": "https://rc-gate.dataloop.ai/api/v1/items/6775484b571407171ac4abe0",
      "dataset": "https://rc-gate.dataloop.ai/api/v1/datasets/67753ec471a6654d3f980dab",
      "type": "text",
      "label": "free-text",
      "coordinates": "This is a photo of Bottomwear from Men's Apparel",
      "metadata": {
        "system": {
          "automated": true,
          "promptId": "1"
        },
        "user": {}
      },
      "creator": "yaya.t@dataloop.ai",
      "createdAt": "2025-01-01T20:27:41.045Z",
      "updatedBy": "yaya.t@dataloop.ai",
      "updatedAt": "2025-01-01T20:27:41.045Z",
      "hash": "6b52365a0a817f839f1ae4a13097412767597f2d",
      "source": "sdk"
    }
  ],
  "annotationsCount": 1,
  "annotated": true
}