{
  "id": "6775496f04951e19ce800e8d",
  "datasetId": "67753ec471a6654d3f980dab",
  "url": "https://rc-gate.dataloop.ai/api/v1/items/6775496f04951e19ce800e8d",
  "dataset": "https://rc-gate.dataloop.ai/api/v1/datasets/67753ec471a6654d3f980dab",
  "createdAt": "2025-01-01T13:55:59.228Z",
  "dir": "/",
  "filename": "/46448.json",
  "type": "file",
  "hidden": false,
  "metadata": {
    "system": {
      "encoding": "7bit",
      "isBinary": false,
      "mimetype": "application/json",
      "originalname": "46448.json",
      "refs": [],
      "shebang": {
        "dltype": "prompt"
      },
      "size": 240,
      "tags": {
        "train": true
      },
      "taskStatusLog": []
    }
  },
  "name": "46448.json",
  "creator": "yaya.t@dataloop.ai",
  "updatedAt": "2025-01-02T05:02:41.537Z",
  "updatedBy": "rubiks@dataloop.ai",
  "stream": "https://rc-gate.dataloop.ai/api/v1/items/6775496f04951e19ce800e8d/stream",
  "thumbnail": "https://rc-gate.dataloop.ai/api/v1/items/6775496f04951e19ce800e8d/thumbnail",
  "annotations": [
    {
      "id": "6775a59c83871cdf0506d6a3",
      "datasetId": "67753ec471a6654d3f980dab",
      "itemId": "6775496f04951e19ce800e8d",
      "url": "https://rc-gate.dataloop.ai/api/v1/annotations/6775a59c83871cdf0506d6a3",
      "item": "https://rc-gate.dataloop.ai/api/v1/items/6775496f04951e19ce800e8d",
      "dataset": "https://rc-gate.dataloop.ai/api/v1/datasets/67753ec471a6654d3f980dab",
      "type": "text",
      "label": "free-text",
      "coordinates": "This is a photo of Watches from Men's Accessories",
      "metadata": {
        "system": {
          "automated": true,
          "promptId": "1"
        },
        "user": {}
      },
      "creator": "yaya.t@dataloop.ai",
      "createdAt": "2025-01-01T20:29:16.524Z",
      "updatedBy": "yaya.t@dataloop.ai",
      "updatedAt": "2025-01-01T20:29:16.524Z",
      "hash": "e1042bebaf19cbbf211d070a4bcfc4aa1dfff843",
      "source": "sdk"
    }
  ],
  "annotationsCount": 1,
  "annotated": true
}