{
  "id": "677551f904951e688480daea",
  "datasetId": "67753ec471a6654d3f980dab",
  "url": "https://rc-gate.dataloop.ai/api/v1/items/677551f904951e688480daea",
  "dataset": "https://rc-gate.dataloop.ai/api/v1/datasets/67753ec471a6654d3f980dab",
  "createdAt": "2025-01-01T14:32:25.586Z",
  "dir": "/",
  "filename": "/4755.json",
  "type": "file",
  "hidden": false,
  "metadata": {
    "system": {
      "encoding": "7bit",
      "isBinary": false,
      "mimetype": "application/json",
      "originalname": "4755.json",
      "refs": [],
      "shebang": {
        "dltype": "prompt"
      },
      "size": 240,
      "tags": {
        "train": true
      },
      "taskStatusLog": []
    }
  },
  "name": "4755.json",
  "creator": "yaya.t@dataloop.ai",
  "updatedAt": "2025-01-02T05:02:41.074Z",
  "updatedBy": "rubiks@dataloop.ai",
  "stream": "https://rc-gate.dataloop.ai/api/v1/items/677551f904951e688480daea/stream",
  "thumbnail": "https://rc-gate.dataloop.ai/api/v1/items/677551f904951e688480daea/thumbnail",
  "annotations": [
    {
      "id": "6775b8750d0617485a6f00ae",
      "datasetId": "67753ec471a6654d3f980dab",
      "itemId": "677551f904951e688480daea",
      "url": "https://rc-gate.dataloop.ai/api/v1/annotations/6775b8750d0617485a6f00ae",
      "item": "https://rc-gate.dataloop.ai/api/v1/items/677551f904951e688480daea",
      "dataset": "https://rc-gate.dataloop.ai/api/v1/datasets/67753ec471a6654d3f980dab",
      "type": "text",
      "label": "free-text",
      "coordinates": "This is a photo of Topwear from Men's Apparel",
      "metadata": {
        "system": {
          "automated": true,
          "promptId": "1"
        },
        "user": {}
      },
      "creator": "yaya.t@dataloop.ai",
      "createdAt": "2025-01-01T21:49:41.088Z",
      "updatedBy": "yaya.t@dataloop.ai",
      "updatedAt": "2025-01-01T21:49:41.088Z",
      "hash": "1dc5438dd9f8ce6db428c46446c71b3c31638cf5",
      "source": "sdk"
    }
  ],
  "annotationsCount": 1,
  "annotated": true
}