{
  "id": "67754c2b5cdbbea443dcbab0",
  "datasetId": "67753ec471a6654d3f980dab",
  "url": "https://rc-gate.dataloop.ai/api/v1/items/67754c2b5cdbbea443dcbab0",
  "dataset": "https://rc-gate.dataloop.ai/api/v1/datasets/67753ec471a6654d3f980dab",
  "createdAt": "2025-01-01T14:07:39.350Z",
  "dir": "/",
  "filename": "/58053.json",
  "type": "file",
  "hidden": false,
  "metadata": {
    "system": {
      "encoding": "7bit",
      "isBinary": false,
      "mimetype": "application/json",
      "originalname": "58053.json",
      "refs": [],
      "shebang": {
        "dltype": "prompt"
      },
      "size": 240,
      "tags": {
        "train": true
      },
      "taskStatusLog": []
    }
  },
  "name": "58053.json",
  "creator": "yaya.t@dataloop.ai",
  "updatedAt": "2025-01-02T05:02:41.574Z",
  "updatedBy": "rubiks@dataloop.ai",
  "stream": "https://rc-gate.dataloop.ai/api/v1/items/67754c2b5cdbbea443dcbab0/stream",
  "thumbnail": "https://rc-gate.dataloop.ai/api/v1/items/67754c2b5cdbbea443dcbab0/thumbnail",
  "annotations": [
    {
      "id": "6775b54a83871c614b06f4c8",
      "datasetId": "67753ec471a6654d3f980dab",
      "itemId": "67754c2b5cdbbea443dcbab0",
      "url": "https://rc-gate.dataloop.ai/api/v1/annotations/6775b54a83871c614b06f4c8",
      "item": "https://rc-gate.dataloop.ai/api/v1/items/67754c2b5cdbbea443dcbab0",
      "dataset": "https://rc-gate.dataloop.ai/api/v1/datasets/67753ec471a6654d3f980dab",
      "type": "text",
      "label": "free-text",
      "coordinates": "This is a photo of Jewellery from Women's Accessories",
      "metadata": {
        "system": {
          "automated": true,
          "promptId": "1"
        },
        "user": {}
      },
      "creator": "yaya.t@dataloop.ai",
      "createdAt": "2025-01-01T21:36:10.737Z",
      "updatedBy": "yaya.t@dataloop.ai",
      "updatedAt": "2025-01-01T21:36:10.737Z",
      "hash": "5f16f6eddd73e2afe7460bf3ebbb1db69eaf321b",
      "source": "sdk"
    }
  ],
  "annotationsCount": 1,
  "annotated": true
}