{
  "id": "677546af04951ef9b97fc320",
  "datasetId": "67753ec471a6654d3f980dab",
  "url": "https://rc-gate.dataloop.ai/api/v1/items/677546af04951ef9b97fc320",
  "dataset": "https://rc-gate.dataloop.ai/api/v1/datasets/67753ec471a6654d3f980dab",
  "createdAt": "2025-01-01T13:44:15.189Z",
  "dir": "/",
  "filename": "/58641.json",
  "type": "file",
  "hidden": false,
  "metadata": {
    "system": {
      "encoding": "7bit",
      "isBinary": false,
      "mimetype": "application/json",
      "originalname": "58641.json",
      "refs": [],
      "shebang": {
        "dltype": "prompt"
      },
      "size": 240,
      "tags": {
        "train": true
      },
      "taskStatusLog": []
    }
  },
  "name": "58641.json",
  "creator": "yaya.t@dataloop.ai",
  "updatedAt": "2025-01-02T05:02:42.027Z",
  "updatedBy": "rubiks@dataloop.ai",
  "stream": "https://rc-gate.dataloop.ai/api/v1/items/677546af04951ef9b97fc320/stream",
  "thumbnail": "https://rc-gate.dataloop.ai/api/v1/items/677546af04951ef9b97fc320/thumbnail",
  "annotations": [
    {
      "id": "6775a4270d0617ab066e93dd",
      "datasetId": "67753ec471a6654d3f980dab",
      "itemId": "677546af04951ef9b97fc320",
      "url": "https://rc-gate.dataloop.ai/api/v1/annotations/6775a4270d0617ab066e93dd",
      "item": "https://rc-gate.dataloop.ai/api/v1/items/677546af04951ef9b97fc320",
      "dataset": "https://rc-gate.dataloop.ai/api/v1/datasets/67753ec471a6654d3f980dab",
      "type": "text",
      "label": "free-text",
      "coordinates": "This is a photo of Socks from Men's Accessories",
      "metadata": {
        "system": {
          "automated": true,
          "promptId": "1"
        },
        "user": {}
      },
      "creator": "yaya.t@dataloop.ai",
      "createdAt": "2025-01-01T20:23:03.998Z",
      "updatedBy": "yaya.t@dataloop.ai",
      "updatedAt": "2025-01-01T20:23:03.998Z",
      "hash": "1117fa31811e6e65e6ff36efacaea41e681a7f69",
      "source": "sdk"
    }
  ],
  "annotationsCount": 1,
  "annotated": true
}